CHANGES.rst
LICENSE
README.rst
setup.cfg
setup.py
src/senaite/__init__.py
src/senaite.lis2a.egg-info/PKG-INFO
src/senaite.lis2a.egg-info/SOURCES.txt
src/senaite.lis2a.egg-info/dependency_links.txt
src/senaite.lis2a.egg-info/entry_points.txt
src/senaite.lis2a.egg-info/namespace_packages.txt
src/senaite.lis2a.egg-info/not-zip-safe
src/senaite.lis2a.egg-info/requires.txt
src/senaite.lis2a.egg-info/top_level.txt
src/senaite/lis2a/__init__.py
src/senaite/lis2a/configure.zcml
src/senaite/lis2a/interfaces.py
src/senaite/lis2a/setuphandlers.py
src/senaite/lis2a/adapters/__init__.py
src/senaite/lis2a/adapters/configure.zcml
src/senaite/lis2a/api/__init__.py
src/senaite/lis2a/api/analysis.py
src/senaite/lis2a/api/message.py
src/senaite/lis2a/interpreter/__init__.py
src/senaite/lis2a/interpreter/lis2a2.py
src/senaite/lis2a/profiles/default/browserlayer.xml
src/senaite/lis2a/profiles/default/metadata.xml
src/senaite/lis2a/profiles/default/senaite.lis2a.install.txt
src/senaite/lis2a/profiles/uninstall/browserlayer.xml
src/senaite/lis2a/profiles/uninstall/metadata.xml
src/senaite/lis2a/profiles/uninstall/senaite.lis2a.uninstall.txt
src/senaite/lis2a/resources/README
src/senaite/lis2a/tests/__init__.py
src/senaite/lis2a/tests/base.py
src/senaite/lis2a/tests/test_doctests.py
src/senaite/lis2a/tests/test_setup.py
src/senaite/lis2a/tests/utils.py
src/senaite/lis2a/tests/doctests/API.rst
src/senaite/lis2a/tests/doctests/PushConsumer.rst
src/senaite/lis2a/tests/resources/abbottm2000.json
src/senaite/lis2a/tests/resources/example_lis2a2_01.txt
src/senaite/lis2a/tests/resources/example_lis2a2_02.txt
src/senaite/lis2a/tests/resources/example_non-lis2a2_01.txt