Metadata-Version: 2.1
Name: senaite.lis2a
Version: 2.0.0
Summary: CLIS LIS2-A results import for SENAITE
Home-page: https://github.com/senaite/senaite.lis2a
Author: RIDING BYTES & NARALABS
Author-email: senaite@senaite.com
License: GPLv2
Keywords: senaite,lims,opensource,LIS2-A
Platform: UNKNOWN
Classifier: Framework :: Plone
Classifier: Framework :: Zope2
Classifier: Programming Language :: Python
Classifier: License :: OSI Approved :: GNU General Public License v2 (GPLv2)
Provides-Extra: test
License-File: LICENSE
